hdi/__init__.py
hdi/extractors.py
hdi/models.py
hdi/utils.py
tabx-1.0.0.dist-info/METADATA
tabx-1.0.0.dist-info/WHEEL
tabx-1.0.0.dist-info/top_level.txt
tabx-1.0.0.dist-info/RECORD
