Metadata-Version: 2.1
Name: tabx
Version: 1.0.0
Summary: Advanced Table Extraction and Text Recognition Library
Author: Tanmay Dumbre
Author-email: tanmaymdumbrek@gmail.com
Requires-Python: >=3.7
Requires-Dist: opencv-python
Requires-Dist: numpy
Requires-Dist: pandas
Requires-Dist: pytesseract
Requires-Dist: doctr
Requires-Dist: camelot-py[cv]
Requires-Dist: tabula-py
Requires-Dist: openpyxl
Requires-Dist: transformers
Requires-Dist: torch
Requires-Dist: pillow
Requires-Dist: pdf2image
